Pattern_Dinkar/__init__.py
Pattern_Dinkar/pattern.py
Pattern_Dinkar-0.1.0.dist-info/METADATA
Pattern_Dinkar-0.1.0.dist-info/WHEEL
Pattern_Dinkar-0.1.0.dist-info/top_level.txt
Pattern_Dinkar-0.1.0.dist-info/RECORD
