Metadata-Version: 2.1
Name: Pattern-Dinkar
Version: 0.1.0
Summary: Sample Package Printing
Home-page: https://github.com/vineet12kotari/dinkar_package
Author: K Dinkar
Author-email: vineetkotari98@gmail.com
Classifier: Programming Language :: Python :: 3
Classifier: License :: OSI Approved :: MIT License
Classifier: Operating System :: OS Independent
Requires-Python: >=3.6
